[  
    {
    "producto":"zapatillas revolution 6",
    "id":"crearID()",
    "categoria":"running",
    "marca":"nike",
    "precio": 21900,
    "cantidad":1, 
    "images":"images/1.jpg"
},
{
    "producto":"zapatillas zoom Winflo 8",
    "id":"crearID()",
    "categoria":"running",
    "marca":"nike",
    "precio":36299,
    "cantidad":1, 
    "images":"images/2.jpg"
},
{
    "producto":"zapatillas supercross 3",
    "id":"crearID()",
    "categoria":"outdoor",
    "marca":"salomon",
    "precio":31499,
    "cantidad":1,
    "images": "images/3.jpg"
},
{
    "producto":"zapatillas gondor II",
    "id":"crearID()",
    "categoria":"outdoor",
    "marca":"topper",
    "precio":17000,
    "cantidad":1, 
    "images":"images/4.jpg"
},
{
    "producto":"botas de hombre ultra venture",
    "id":"crearID()",
    "categoria":"trekking",
    "marca":"montagne",
    "precio":37000,
    "cantidad":1,
    "images":"images/5.jpg"
},

{
    "producto":"botas ona",
    "id":"crearID()",
    "categoria":"trekking",
    "marca":"montagne",
    "precio":22110,
    "cantidad":1,
    "images":"images/6.jpg"
},
{
    "producto":"botas Craddock",
    "id":"crearID()",
    "categoria":"urbano",
    "marca":"montagne",
    "precio":12037,
    "cantidad":1,
    "images":"images/7.jpg"
},
{
    "producto":"ojota azul Adidas Adilette Shower",
    "id":"crearID()",
    "categoria":"urbano",
    "marca":"adidas",
    "precio":7500,
    "cantidad":1,
    "images":"images/8.jpg"
},
{
    "producto":"crocs crocband clog",
    "id":"crearID()",
    "categoria":"urbano",
    "marca":"crocs",
    "precio":9899,
    "cantidad":1,
    "images":"images/9.jpg"
},
{
    "producto":"zapatilla negra Adidas superstart",
    "id":"crearID()",
    "categoria":"urbano",
    "marca":"adidas",
    "precio":25899,
    "cantidad":1,
    "images":"images/10.jpg"
}

]

